2a/archi/projet/ER_1OCTET/er_1octet.vhd
library IEEE;
use IEEE.STD_LOGIC_1164.ALL;

entity er_1octet is
  port ( rst : in std_logic ;
         clk : in std_logic ;
         en : in std_logic ;
         din : in std_logic_vector (7 downto 0) ;
         miso : in std_logic ;
         sclk : out std_logic ;
         mosi : out std_logic ;
         dout : out std_logic_vector (7 downto 0) ;
         busy : out std_logic);
end er_1octet;

architecture behavioral_3 of er_1octet is
  type t_etat is (REPOS, RECEPTION, ENVOI);
  signal registre : std_logic_vector (7 downto 0);
  signal etat : t_etat;
begin
  process(rst, clk)
    variable cpt : natural;
  begin
    -- reset
    if (rst = '0') then
      etat <= REPOS;
      sclk <= '1';
      busy <= '0';

    -- horloge montante
    elsif (rising_edge(clk)) then
      case etat is
        when REPOS =>
          if (en = '1') then
            cpt := 7;
            busy <= '1';
            registre <= din;
            sclk <= '0';
            mosi <= din(cpt);
            etat <= RECEPTION;
          end if;

        when RECEPTION =>
          sclk <= '1';
          if (cpt > 0) then
            registre(cpt) <= miso;
            cpt := cpt - 1;
            etat <= ENVOI;
          else
            busy <= '0';
            dout(7 downto 1) <= registre(7 downto 1);
            dout(0) <= miso;
            etat <= REPOS;
          end if;

        when ENVOI =>
          sclk <= '0';
          mosi <= registre(cpt);
          etat <= RECEPTION;
      end case;
    end if;
  end process;
end behavioral_3;

2a/archi/mini-projet/ER_1OCTET/test_er_1octet_automate.vhd
library IEEE;
use IEEE.STD_LOGIC_1164.ALL;

entity test_er_1octet2 is
  end test_er_1octet2;

architecture behavior of test_er_1octet2 is

  component er_1octet
    port ( rst : in std_logic;
           clk : in std_logic;
           en : in std_logic;
           din : in std_logic_vector (7 downto 0);
           miso : in std_logic;
           sclk : out std_logic;
           mosi : out std_logic;
           dout : out std_logic_vector (7 downto 0);
           busy : out std_logic);
  end component;

  --Inputs
  signal clk : std_logic := '0';
  signal reset : std_logic := '0';
  signal en_er : std_logic := '0';
  signal din_er : std_logic_vector(7 downto 0) := (others => '0');
  signal miso : std_logic := '0';

  --Outputs
  signal busy_er : std_logic;
  signal dout_er : std_logic_vector(7 downto 0);
  signal sclk : std_logic;
  signal mosi : std_logic;

  -- Clock period definitions
  constant clk_period : time := 10 ns;

  -- types
  type t_etat is (debut, attente_active, echange_octet, fin);
        
  -- signaux internes   
  signal etat : t_etat;

  signal mosi_ref : std_logic;
  signal sclk_ref : std_logic;
  signal busy_ref : std_logic;
  signal dout_ref : std_logic_vector(7 downto 0);

begin

  m : er_1octet
  port map ( clk => clk,
             rst => reset,
             en => en_er,
             busy => busy_er,
             din => din_er,
             dout => dout_er,
             sclk => sclk,
             miso => miso,
             mosi => mosi
           );

  clk_process : process
  begin
    clk <= '0';
    wait for clk_period/2;
    clk <= '1';
    wait for clk_period/2;
  end process;

  reset <= '0', '1' after 100 ns;

  -- process permettant d'échanger 2 octets
  stim_proc: process(clk, reset)
    -- variables 
    variable cpt_att : natural;
    variable cpt_octet : natural;
  begin
    if(reset = '0') then
      cpt_octet := 0;
      en_er <= '0';
      din_er <= (others => 'U');
      etat <= debut;
    elsif(rising_edge(clk)) then

      case  etat is

        when debut =>
          -- attente de 10 cycles de l'horloge
          -- avant le premier octet
          cpt_att := 10;
          cpt_octet := 0;
          etat <= attente_active;

        when attente_active => 
          cpt_att := cpt_att - 1;
          if(cpt_att = 0) then
            -- on a attendu assez longtemps

            -- valeur de l'octet envoyé
            if(cpt_octet = 0) then
              din_er <= "10110101";
            else
              din_er <= "01010100";
            end if;
            -- on lance l'échange d'un octet en activant
            -- le sous-composant
            en_er <= '1';
            etat <= echange_octet;
          end if;

        when echange_octet => 
          -- on rabaisse l'ordre passé au sous-composant
          en_er <= '0';
          din_er <= (others => 'U');

          if(en_er = '0' and busy_er ='0') then
            -- échange d'1 octet terminé

            -- on prépare la suite
            if(cpt_octet = 0) then
              -- il reste des octets à transmettre
              cpt_octet := cpt_octet + 1;
              -- attente de 5 cycles entre les deux octets
              cpt_att := 5;
              etat <= attente_active;
            else
              -- on a envoyé 2 octets, c'est fini
              etat <= fin;
            end if;

          end if;

        when fin => null;

      end case;

    end if;
  end process;

  -- process qui génère le signal miso
  genere_miso : process(clk, reset)
    variable cpt : natural;

  begin
    if(reset = '0') then
      miso <= '0';
      cpt := 0;
    elsif(falling_edge(clk)) then
      cpt := (cpt + 1) mod 7;
      if(cpt < 3) then
        miso <= '0';
      else
        miso <= '1';
      end if;                  
    end if;
  end process genere_miso;

  --
  -- pour vérifier si mosi, sclk, busy et dout sont corrects
mosi_ref  <=  'U' after 0 fs,
              '1' after 215000000 fs,
              '0' after 235000000 fs,
              '1' after 255000000 fs,
              '0' after 295000000 fs,
              '1' after 315000000 fs,
              '0' after 335000000 fs,
              '1' after 355000000 fs,
              '0' after 435000000 fs,
              '1' after 455000000 fs,
              '0' after 475000000 fs,
              '1' after 495000000 fs,
              '0' after 515000000 fs,
              '1' after 535000000 fs,
              '0' after 555000000 fs;

sclk_ref <= '1' after 0 fs,
            '0' after 215000000 fs,
            '1' after 225000000 fs,
            '0' after 235000000 fs,
            '1' after 245000000 fs,
            '0' after 255000000 fs,
            '1' after 265000000 fs,
            '0' after 275000000 fs,
            '1' after 285000000 fs,
            '0' after 295000000 fs,
            '1' after 305000000 fs,
            '0' after 315000000 fs,
            '1' after 325000000 fs,
            '0' after 335000000 fs,
            '1' after 345000000 fs,
            '0' after 355000000 fs,
            '1' after 365000000 fs,
            '0' after 435000000 fs,
            '1' after 445000000 fs,
            '0' after 455000000 fs,
            '1' after 465000000 fs,
            '0' after 475000000 fs,
            '1' after 485000000 fs,
            '0' after 495000000 fs,
            '1' after 505000000 fs,
            '0' after 515000000 fs,
            '1' after 525000000 fs,
            '0' after 535000000 fs,
            '1' after 545000000 fs,
            '0' after 555000000 fs,
            '1' after 565000000 fs,
            '0' after 575000000 fs,
            '1' after 585000000 fs;

  busy_ref <= '0' after 0 fs,
              '1' after 215000000 fs,
              '0' after 365000000 fs,
              '1' after 435000000 fs,
              '0' after 585000000 fs;

  dout_ref <= "UUUUUUUU" after 0 fs,
              "10110011" after 365000000 fs,
              "00110110" after 585000000 fs;

  process(clk)
  begin
    if(falling_edge(clk)) then
      assert(mosi = mosi_ref) report "mosi faux"
      severity error;
      assert(sclk = sclk_ref) report "sclk faux"
      severity error;
      assert(busy_er = busy_ref) report "busy faux"
      severity error;
      assert(dout_er = dout_ref) report "dout faux"
      severity error;
    end if;
  end process;

end behavior;

2a/archi/mini-projet/ER_1OCTET/output2.vcd
$date
  Tue Nov  4 15:27:27 2025
$end
$version
  GHDL v0
$end
$timescale
  1 fs
$end
$scope module standard $end
$upscope $end
$scope module textio $end
$upscope $end
$scope module std_logic_1164 $end
$upscope $end
$scope module test_er_1octet2 $end
$var reg 1 ! clk $end
$var reg 1 " reset $end
$var reg 1 # en_er $end
$var reg 8 $ din_er[7:0] $end
$var reg 1 % miso $end
$var reg 1 & busy_er $end
$var reg 8 ' dout_er[7:0] $end
$var reg 1 ( sclk $end
$var reg 1 ) mosi $end
$comment etat is not handled $end
$var reg 1 * mosi_ref $end
$var reg 1 + sclk_ref $end
$var reg 1 , busy_ref $end
$var reg 8 - dout_ref[7:0] $end
$scope module m $end
$var reg 1 . rst $end
$var reg 1 / clk $end
$var reg 1 0 en $end
$var reg 8 1 din[7:0] $end
$var reg 1 2 miso $end
$var reg 1 3 sclk $end
$var reg 1 4 mosi $end
$var reg 8 5 dout[7:0] $end
$var reg 1 6 busy $end
$var reg 8 7 registre[7:0] $end
$comment etat is not handled $end
$upscope $end
$upscope $end
$enddefinitions $end
#0
0!
0"
0#
bUUUUUUUU $
0%
0&
bUUUUUUUU '
1(
U)
U*
1+
0,
bUUUUUUUU -
0.
0/
00
bUUUUUUUU 1
02
13
U4
bUUUUUUUU 5
06
bUUUUUUUU 7
#5000000
1!
1/
#10000000
0!
0/
#15000000
1!
1/
#20000000
0!
0/
#25000000
1!
1/
#30000000
0!
0/
#35000000
1!
1/
#40000000
0!
0/
#45000000
1!
1/
#50000000
0!
0/
#55000000
1!
1/
#60000000
0!
0/
#65000000
1!
1/
#70000000
0!
0/
#75000000
1!
1/
#80000000
0!
0/
#85000000
1!
1/
#90000000
0!
0/
#95000000
1!
1/
#100000000
0!
1"
1.
0/
#105000000
1!
1/
#110000000
0!
0/
#115000000
1!
1/
#120000000
0!
1%
0/
12
#125000000
1!
1/
#130000000
0!
0/
#135000000
1!
1/
#140000000
0!
0/
#145000000
1!
1/
#150000000
0!
0/
#155000000
1!
1/
#160000000
0!
0%
0/
02
#165000000
1!
1/
#170000000
0!
0/
#175000000
1!
1/
#180000000
0!
0/
#185000000
1!
1/
#190000000
0!
1%
0/
12
#195000000
1!
1/
#200000000
0!
0/
#205000000
1!
1#
b10110101 $
1/
10
b10110101 1
#210000000
0!
0/
#215000000
1!
0#
bUUUUUUUU $
1&
0(
1)
1*
0+
1,
1/
00
bUUUUUUUU 1
03
14
16
b10110101 7
#220000000
0!
0/
#225000000
1!
1(
1+
1/
13
#230000000
0!
0%
0/
02
#235000000
1!
0(
0)
0*
0+
1/
03
04
#240000000
0!
0/
#245000000
1!
1(
1+
1/
13
#250000000
0!
0/
#255000000
1!
0(
1)
1*
0+
1/
03
14
#260000000
0!
1%
0/
12
#265000000
1!
1(
1+
1/
13
#270000000
0!
0/
#275000000
1!
0(
0+
1/
03
#280000000
0!
0/
#285000000
1!
1(
1+
1/
13
#290000000
0!
0/
#295000000
1!
0(
0)
0*
0+
1/
03
04
#300000000
0!
0%
0/
02
#305000000
1!
1(
1+
1/
13
#310000000
0!
0/
#315000000
1!
0(
1)
1*
0+
1/
03
14
#320000000
0!
0/
#325000000
1!
1(
1+
1/
13
b10110001 7
#330000000
0!
1%
0/
12
#335000000
1!
0(
0)
0*
0+
1/
03
04
#340000000
0!
0/
#345000000
1!
1(
1+
1/
13
b10110011 7
#350000000
0!
0/
#355000000
1!
0(
1)
1*
0+
1/
03
14
#360000000
0!
0/
#365000000
1!
0&
b10110011 '
1(
1+
0,
b10110011 -
1/
13
b10110011 5
06
#370000000
0!
0%
0/
02
#375000000
1!
1/
#380000000
0!
0/
#385000000
1!
1/
#390000000
0!
0/
#395000000
1!
1/
#400000000
0!
1%
0/
12
#405000000
1!
1/
#410000000
0!
0/
#415000000
1!
1/
#420000000
0!
0/
#425000000
1!
1#
b01010100 $
1/
10
b01010100 1
#430000000
0!
0/
#435000000
1!
0#
bUUUUUUUU $
1&
0(
0)
0*
0+
1,
1/
00
bUUUUUUUU 1
03
04
16
b01010100 7
#440000000
0!
0%
0/
02
#445000000
1!
1(
1+
1/
13
#450000000
0!
0/
#455000000
1!
0(
1)
1*
0+
1/
03
14
#460000000
0!
0/
#465000000
1!
1(
1+
1/
13
b00010100 7
#470000000
0!
1%
0/
12
#475000000
1!
0(
0)
0*
0+
1/
03
04
#480000000
0!
0/
#485000000
1!
1(
1+
1/
13
b00110100 7
#490000000
0!
0/
#495000000
1!
0(
1)
1*
0+
1/
03
14
#500000000
0!
0/
#505000000
1!
1(
1+
1/
13
#510000000
0!
0%
0/
02
#515000000
1!
0(
0)
0*
0+
1/
03
04
#520000000
0!
0/
#525000000
1!
1(
1+
1/
13
#530000000
0!
0/
#535000000
1!
0(
1)
1*
0+
1/
03
14
#540000000
0!
1%
0/
12
#545000000
1!
1(
1+
1/
13
#550000000
0!
0/
#555000000
1!
0(
0)
0*
0+
1/
03
04
#560000000
0!
0/
#565000000
1!
1(
1+
1/
13
b00110110 7
#570000000
0!
0/
#575000000
1!
0(
0+
1/
03
#580000000
0!
0%
0/
02
#585000000
1!
0&
b00110110 '
1(
1+
0,
b00110110 -
1/
13
b00110110 5
06
#590000000
0!
0/
#595000000
1!
1/
#600000000
0!
0/
#605000000
1!
1/
#610000000
0!
1%
0/
12
#615000000
1!
1/
#620000000
0!
0/
#625000000
1!
1/
#630000000
0!
0/
#635000000
1!
1/
#640000000
0!
0/
#645000000
1!
1/
#650000000
0!
0%
0/
02
#655000000
1!
1/
#660000000
0!
0/
#665000000
1!
1/
#670000000
0!
0/
#675000000
1!
1/
#680000000
0!
1%
0/
12
#685000000
1!
1/
#690000000
0!
0/
#695000000
1!
1/
#700000000
0!
0/
#705000000
1!
1/
#710000000
0!
0/
#715000000
1!
1/
#720000000
0!
0%
0/
02
#725000000
1!
1/
#730000000
0!
0/
#735000000
1!
1/
#740000000
0!
0/
#745000000
1!
1/
#750000000
0!
1%
0/
12
#755000000
1!
1/
#760000000
0!
0/
#765000000
1!
1/
#770000000
0!
0/
#775000000
1!
1/
#780000000
0!
0/
#785000000
1!
1/
#790000000
0!
0%
0/
02
#795000000
1!
1/
#800000000
0!
0/
#805000000
1!
1/
#810000000
0!
0/
#815000000
1!
1/
#820000000
0!
1%
0/
12
#825000000
1!
1/
#830000000
0!
0/
#835000000
1!
1/
#840000000
0!
0/
#845000000
1!
1/
#850000000
0!
0/
#855000000
1!
1/
#860000000
0!
0%
0/
02
#865000000
1!
1/
#870000000
0!
0/
#875000000
1!
1/
#880000000
0!
0/
#885000000
1!
1/
#890000000
0!
1%
0/
12
#895000000
1!
1/
#900000000
0!
0/
#905000000
1!
1/
#910000000
0!
0/
#915000000
1!
1/
#920000000
0!
0/
#925000000
1!
1/
#930000000
0!
0%
0/
02
#935000000
1!
1/
#940000000
0!
0/
#945000000
1!
1/
#950000000
0!
0/
#955000000
1!
1/
#960000000
0!
1%
0/
12
#965000000
1!
1/
#970000000
0!
0/
#975000000
1!
1/
#980000000
0!
0/
#985000000
1!
1/
#990000000
0!
0/
#995000000
1!
1/
#1000000000
0!
0%
0/
02
