2a/archi/tp3-4/composants/diviseurClk.vhd
library IEEE;
use IEEE.std_logic_1164.all;

entity diviseurClk is
  -- facteur : ratio entre la fréquence de l'horloge origine et celle
  --           de l'horloge générée
  --  ex : 100 MHz -> 1Hz : 100 000 000
  --  ex : 100 MHz -> 1kHz : 100 000
  generic(facteur : natural);
  port (
    clk, reset : in  std_logic;
    nclk       : out std_logic
  );
end diviseurClk;

architecture arch_divClk of diviseurClk is

  signal top : std_logic := '0';
  
begin  

  div : process (clk, reset)
    variable cpt : integer range 0 to facteur-1 := 0;
  begin 
    if reset = '0' then
      nclk <= '0';
      cpt := 0;
    elsif rising_edge(clk) then
      if(cpt = facteur - 1) then
        nclk <= '1';
        cpt := 0;
      else
        cpt := cpt + 1;
        nclk <= '0';
      end if;
    end if;
  end process;

end arch_divClk;

2a/projet_archi/UART/clkUnit.vhd
library IEEE;
use IEEE.std_logic_1164.all;

entity clkUnit is
 port(
    clk, reset : in  std_logic;
    enableTX   : out std_logic;
    enableRX   : out std_logic);
end clkUnit;

architecture behavorial of clkUnit is

  component diviseurClk is
    generic(facteur : natural);
    port(
      clk, reset : in  std_logic;
      nclk       : out std_logic);
  end component;

  signal    clkRX : std_logic;
  signal    clkTX : std_logic;

begin

  diviseurClkRx : diviseurClk
    generic map (10)
    port map(clk => clk, reset => reset, nclk => enableRX);
  
  diviseurClkTx : diviseurClk
    generic map (160)
    port map(clk => clk, reset => reset, nclk => enableTX);

end behavorial;

2a/projet_archi/UART/controleReception.vhd
library IEEE;
use IEEE.std_logic_1164.all;
use IEEE.numeric_std.all;

entity controleReception is
  port (
    clk 		: in std_logic;
    reset 	: in std_logic;
    read 		: in std_logic;
    tmpClk 	: in std_logic;
    tmpRxd 	: in std_logic;
    FErr 		: out std_logic;
    OErr 		: out std_logic;
    DRdy 		: out std_logic;
    data 		: out std_logic_vector(7 downto 0));
end controleReception;

architecture behavioral of controleReception is

  signal buf : std_logic_vector(8 downto 0) := (others => 'U');

  type t_etat is (REPOS, RECEPTION, ATTENTE);
  signal etat : t_etat := REPOS;
  
begin
    
    process (clk, reset) is

      variable compteur : natural := 9;
      variable compteur_read : natural := 5;

    begin
      
      if (reset = '0') then
        DRdy <= '0';
        FErr <= '0';
        OErr <= '0';
        compteur := 8;
        compteur_read := 5;
        data <= (others => '0');
        etat <= REPOS;
      elsif (rising_edge(clk)) then
        case etat is
          when REPOS =>
          if (tmpClk = '1' and tmpRxd = '0') then
              data <= (others => '0');
              DRdy <= '0';
              FErr <= '0';
              OErr <= '0';
              etat <= RECEPTION;
              compteur := 8;
            end if;
          when RECEPTION =>
            -- donnée positionnée sur tmpRxd au front montant de tmpClk
            if (tmpClk = '1') then
              -- on la lit
              buf(compteur) <= tmpRxd;
              if (compteur = 0) then
                -- on est sur le bit de stop
                if (tmpRxd = '1') then
                  -- bit de stop correct
                  data <= buf(8 downto 1);
                  compteur_read := 5;
                  DRdy <= '1';
                  FErr <= '0';
                  OErr <= '0';
                  etat <= ATTENTE;
                else
                  -- bit de stop incorrect
                  FErr <= '1';
                  etat <= REPOS;
                end if;
              else
                -- on est sur un autre bit : start ou donnée
                compteur := compteur - 1;
              end if;
            end if;
          when ATTENTE =>
            compteur_read := compteur_read - 1;
            if (compteur_read = 0) then
              OErr <= '1';
              DRdy <= '0';
              etat <= REPOS;
              buf <= (others => '0');
            elsif (read = '1') then
              DRdy <= '0';
              etat <= REPOS;
              buf <= (others => '0');
            end if;
        end case;
      end if;
    end process;
end behavioral;

2a/projet_archi/UART/compteur16.vhd
library IEEE;
use IEEE.std_logic_1164.all;
use IEEE.numeric_std.all;

entity compteur16 is
  port (
    clk 	: in std_logic;
    enable 	: in std_logic;
    reset 	: in std_logic;
    RxD 	: in std_logic;
    tmpClk 	: out std_logic;
    tmpRxd 	: out std_logic);
end compteur16;

architecture behavioral of compteur16 is
  
  type t_etat is (REPOS, COMPTAGE);

  signal etat : t_etat := REPOS;
  signal tmpClk_i : std_logic;
  
  
begin

  tmpClk <= tmpClk_i;
  
  process (clk, reset) is

    variable compteur : natural;

  begin

    if (reset = '0') then
      tmpClk_i <= '1';
      etat <= REPOS;
      compteur := 8;
      tmpRxd <= 'U';
    elsif (rising_edge(clk)) then
      case etat is
        when REPOS =>
          if (enable = '1' and RxD = '0') then
            etat <= COMPTAGE;
          end if;
        when COMPTAGE =>
          if (tmpClk_i = '1') then
            tmpClk_i <= '0';
          end if;
          if (enable = '1') then
            compteur := compteur - 1;
            if (compteur = 0) then
              compteur := 16;
              if (tmpClk_i = '0') then
                tmpRxd <= RxD;
                tmpClk_i <= '1';
              end if;
            end if;
          end if;
      end case;
    end if;
  end process;
 
end behavioral;

2a/projet_archi/UART/RxUnit.vhd
library IEEE;
use IEEE.std_logic_1164.all;

entity RxUnit is
  port (
    clk, reset       : in  std_logic;
    enable           : in  std_logic;
    read             : in  std_logic;
    rxd              : in  std_logic;
    data             : out std_logic_vector(7 downto 0);
    Ferr, OErr, DRdy : out std_logic);
end RxUnit;

architecture behavorial of RxUnit is

  signal tmpClk, tmpRxd : std_logic;
  
  component compteur16 is
  port (
    clk 	  : in std_logic;
    enable 	: in std_logic;
    reset 	: in std_logic;
    RxD 	  : in std_logic;
    tmpClk 	: out std_logic;
    tmpRxd 	: out std_logic);
  end component;
  
  component controleReception is
  port (
    clk 		: in std_logic;
    reset 	: in std_logic;
    read 		: in std_logic;
    tmpClk 	: in std_logic;
    tmpRxd 	: in std_logic;
    FErr 		: out std_logic;
    OErr 		: out std_logic;
    DRdy 		: out std_logic;
    data 		: out std_logic_vector(7 downto 0));
  end component;

begin

  compteur16Inst : compteur16
    port map(
      clk => clk,
      enable => enable,
      reset => reset,
      RxD => rxd,
      tmpClk => tmpClk,
      tmpRxd => tmpRxd);
  
  controleReceptionInst : controleReception
    port map(
      clk => clk,
      reset => reset,
      read => read,
      tmpClk => tmpClk,
      tmpRxd => tmpRxd,
      FErr => FErr,
      OErr => OErr,
      DRdy => DRdy,
      data => data);

end behavorial;

2a/projet_archi/UART/testRxUnit.vhd
--------------------------------------------------------------------------------
-- Company: 
-- Engineer:
--
-- Create Date:   12:09:49 10/31/2018
-- Design Name:   
-- Module Name:   testTxUnit.vhd
-- Project Name:  uart
-- Target Device:  
-- Tool versions:  
-- Description:   
-- 
-- VHDL Test Bench Created by ISE for module: TxUnit
-- 
-- Dependencies:
-- 
-- Revision:
-- Revision 0.01 - File Created
-- Additional Comments:
--
-- Notes: 
-- This testbench has been automatically generated using types std_logic and
-- std_logic_vector for the ports of the unit under test.  Xilinx recommends
-- that these types always be used for the top-level I/O of a design in order
-- to guarantee that the testbench will bind correctly to the post-implementation 
-- simulation model.
--------------------------------------------------------------------------------
LIBRARY ieee;
USE ieee.std_logic_1164.ALL;

-- Uncomment the following library declaration if using
-- arithmetic functions with Signed or Unsigned values
--USE ieee.numeric_std.ALL;

ENTITY testRxUnit IS
END testRxUnit;

ARCHITECTURE behavior OF testRxUnit IS 

  -- Component Declaration for the Unit Under Test (UUT)

  COMPONENT RxUnit
    PORT(
         clk : IN  std_logic;
         reset : IN  std_logic;
         enable : IN  std_logic;
         read : IN  std_logic;
         rxd : IN  std_logic;
         data : OUT  std_logic_vector(7 downto 0);
         Ferr : OUT  std_logic;
         OErr : OUT  std_logic;
         DRdy : OUT  std_logic
        );
    END COMPONENT;
  
  COMPONENT clkUnit
  PORT(
        clk : IN  std_logic;
        reset : IN  std_logic;
        enableTX : OUT  std_logic;
        enableRX : OUT  std_logic
      );
  END COMPONENT;	

  signal clk : std_logic := '0';
  signal reset : std_logic := '0';
  signal enableTx : std_logic := '0';
  signal enableRx : std_logic := '0';
  signal read : std_logic := '0';
  signal data : std_logic_vector(7 downto 0) := (others => '0');

  signal rxd : std_logic := '1';
  signal FErr : std_logic := '0';
  signal OErr : std_logic := '0';
  signal DRdy : std_logic := '0';

  -- Clock period definitions
  constant clk_period : time := 10 ns;

BEGIN

-- Instantiate the Unit Under Test
  uut0: RxUnit PORT MAP (
        clk => clk,
        reset => reset,
        enable => enableRX,
        read => read,
        rxd => rxd,
        data => data,
        FErr => FErr,
        OErr => OErr,
        DRdy => DRdy
      );

  -- Instantiate the clkUnit
  clkUnit1: clkUnit PORT MAP (
        clk => clk,
        reset => reset,
        enableTX => enableTX,
        enableRX => enableRX
      );
    
  -- Clock process definitions
  clk_process : process
  begin
    clk <= '0';
    wait for clk_period/2;
    clk <= '1';
    wait for clk_period/2;
  end process;


  -- Stimulus process
  stim_proc : process
  begin		
    -- maintien du reset durant 100 ns.
    wait for 100 ns;	
    reset <= '1';

    wait for 200 ns;

    -- bit de debut '0'
    if (not (enableTX = '1')) then
      wait until enableTX = '1';
    end if;
    rxd <= '0';
    wait for 10 * clk_period;

    -- envoi de 01010101
    if (not (enableTX = '1')) then
      wait until enableTX = '1';
    end if;
    rxd <= '0';
    wait for 10 * clk_period;

    if (not (enableTX = '1')) then
      wait until enableTX = '1';
    end if;
    rxd <= '1';
    wait for 10 * clk_period;

    if (not (enableTX = '1')) then
      wait until enableTX = '1';
    end if;
    rxd <= '0';
    wait for 10 * clk_period;

    if (not (enableTX = '1')) then
      wait until enableTX = '1';
    end if;
    rxd <= '1';
    wait for 10 * clk_period;

    if (not (enableTX = '1')) then
      wait until enableTX = '1';
    end if;
    rxd <= '0';
    wait for 10 * clk_period;

    if (not (enableTX = '1')) then
      wait until enableTX = '1';
    end if;
    rxd <= '1';
    wait for 10 * clk_period;

    if (not (enableTX = '1')) then
      wait until enableTX = '1';
    end if;
    rxd <= '0';
    wait for 10 * clk_period;

    if (not (enableTX = '1')) then
      wait until enableTX = '1';
    end if;
    rxd <= '1';
    wait for 10 * clk_period;
    
    -- bit de stop
    if (not (enableTX = '1')) then
      wait until enableTX = '1';
    end if;
    rxd <= '1';

    -- Attente pour le read a 1
    wait for 80 * clk_period;
    if (not (enableRX = '1')) then
      wait until enableRX = '1';
    end if;
    wait for 2 * clk_period;

    -- reception
    read <= '1';
    wait for 5 * clk_period;
    read <= '0';

    -- maintien du reset durant 100 ns.
    wait for 100 ns;	
    reset <= '1';

    wait for 200 ns;

    -- bit de debut '0'
    if (not (enableTX = '1')) then
      wait until enableTX = '1';
    end if;
    rxd <= '0';
    wait for 10 * clk_period;

    -- envoi de 01010101
    if (not (enableTX = '1')) then
      wait until enableTX = '1';
    end if;
    rxd <= '0';
    wait for 10 * clk_period;

    if (not (enableTX = '1')) then
      wait until enableTX = '1';
    end if;
    rxd <= '1';
    wait for 10 * clk_period;

    if (not (enableTX = '1')) then
      wait until enableTX = '1';
    end if;
    rxd <= '0';
    wait for 10 * clk_period;

    if (not (enableTX = '1')) then
      wait until enableTX = '1';
    end if;
    rxd <= '1';
    wait for 10 * clk_period;

    if (not (enableTX = '1')) then
      wait until enableTX = '1';
    end if;
    rxd <= '0';
    wait for 10 * clk_period;

    if (not (enableTX = '1')) then
      wait until enableTX = '1';
    end if;
    rxd <= '1';
    wait for 10 * clk_period;

    if (not (enableTX = '1')) then
      wait until enableTX = '1';
    end if;
    rxd <= '0';
    wait for 10 * clk_period;

    if (not (enableTX = '1')) then
      wait until enableTX = '1';
    end if;
    rxd <= '1';
    wait for 10 * clk_period;
    
    -- bit de stop faux
    if (not (enableTX = '1')) then
      wait until enableTX = '1';
    end if;
    rxd <= '0';

    -- Attente pour le read a 1
    wait for 80 * clk_period;
    if (not (enableRX = '1')) then
      wait until enableRX = '1';
    end if;
    wait for 2 * clk_period;

    -- reception
    read <= '1';
    wait for 5 * clk_period;
    read <= '0';

    -- maintien du reset durant 100 ns.
    wait for 100 ns;	
    reset <= '1';

    wait for 200 ns;

    -- bit de debut '0'
    if (not (enableTX = '1')) then
      wait until enableTX = '1';
    end if;
    rxd <= '0';
    wait for 10 * clk_period;

    -- envoi de 01010101
    if (not (enableTX = '1')) then
      wait until enableTX = '1';
    end if;
    rxd <= '0';
    wait for 10 * clk_period;

    if (not (enableTX = '1')) then
      wait until enableTX = '1';
    end if;
    rxd <= '1';
    wait for 10 * clk_period;

    if (not (enableTX = '1')) then
      wait until enableTX = '1';
    end if;
    rxd <= '0';
    wait for 10 * clk_period;

    if (not (enableTX = '1')) then
      wait until enableTX = '1';
    end if;
    rxd <= '1';
    wait for 10 * clk_period;

    if (not (enableTX = '1')) then
      wait until enableTX = '1';
    end if;
    rxd <= '0';
    wait for 10 * clk_period;

    if (not (enableTX = '1')) then
      wait until enableTX = '1';
    end if;
    rxd <= '1';
    wait for 10 * clk_period;

    if (not (enableTX = '1')) then
      wait until enableTX = '1';
    end if;
    rxd <= '0';
    wait for 10 * clk_period;

    if (not (enableTX = '1')) then
      wait until enableTX = '1';
    end if;
    rxd <= '1';
    wait for 10 * clk_period;
    
    -- bit de stop
    if (not (enableTX = '1')) then
      wait until enableTX = '1';
    end if;
    rxd <= '1';

    -- Attente pour le read qui n'arrivera jamais
    wait for 80 * clk_period;
    if (not (enableRX = '1')) then
      wait until enableRX = '1';
    end if;
    wait for 2 * clk_period;

    wait;
  end process;

END;

2a/projet_archi/UART/output.vcd
$date
  Tue Jan 13 14:42:56 2026
$end
$version
  GHDL v0
$end
$timescale
  1 fs
$end
$scope module standard $end
$upscope $end
$scope module textio $end
$upscope $end
$scope module std_logic_1164 $end
$upscope $end
$scope module numeric_std $end
$upscope $end
$scope module testrxunit $end
$var reg 1 ! clk $end
$var reg 1 " reset $end
$var reg 1 # enabletx $end
$var reg 1 $ enablerx $end
$var reg 1 % read $end
$var reg 8 & data[7:0] $end
$var reg 1 ' rxd $end
$var reg 1 ( ferr $end
$var reg 1 ) oerr $end
$var reg 1 * drdy $end
$scope module uut0 $end
$var reg 1 + clk $end
$var reg 1 , reset $end
$var reg 1 - enable $end
$var reg 1 . read $end
$var reg 1 / rxd $end
$var reg 8 0 data[7:0] $end
$var reg 1 1 ferr $end
$var reg 1 2 oerr $end
$var reg 1 3 drdy $end
$var reg 1 4 tmpclk $end
$var reg 1 5 tmprxd $end
$scope module compteur16inst $end
$var reg 1 6 clk $end
$var reg 1 7 enable $end
$var reg 1 8 reset $end
$var reg 1 9 rxd $end
$var reg 1 : tmpclk $end
$var reg 1 ; tmprxd $end
$comment etat is not handled $end
$var reg 1 < tmpclk_i $end
$upscope $end
$scope module controlereceptioninst $end
$var reg 1 = clk $end
$var reg 1 > reset $end
$var reg 1 ? read $end
$var reg 1 @ tmpclk $end
$var reg 1 A tmprxd $end
$var reg 1 B ferr $end
$var reg 1 C oerr $end
$var reg 1 D drdy $end
$var reg 8 E data[7:0] $end
$var reg 9 F buf[8:0] $end
$comment etat is not handled $end
$upscope $end
$upscope $end
$scope module clkunit1 $end
$var reg 1 G clk $end
$var reg 1 H reset $end
$var reg 1 I enabletx $end
$var reg 1 J enablerx $end
$var reg 1 K clkrx $end
$var reg 1 L clktx $end
$scope module diviseurclkrx $end
$var reg 1 M clk $end
$var reg 1 N reset $end
$var reg 1 O nclk $end
$var reg 1 P top $end
$upscope $end
$scope module diviseurclktx $end
$var reg 1 Q clk $end
$var reg 1 R reset $end
$var reg 1 S nclk $end
$var reg 1 T top $end
$upscope $end
$upscope $end
$upscope $end
$enddefinitions $end
#0
0!
0"
0#
0$
0%
b00000000 &
1'
0(
0)
0*
0+
0,
0-
0.
1/
b00000000 0
01
02
03
14
U5
06
07
08
19
1:
U;
1<
0=
0>
0?
1@
UA
0B
0C
0D
b00000000 E
bUUUUUUUUU F
0G
0H
0I
0J
UK
UL
0M
0N
0O
0P
0Q
0R
0S
0T
#5000000
1!
1+
16
1=
1G
1M
1Q
#10000000
0!
0+
06
0=
0G
0M
0Q
#15000000
1!
1+
16
1=
1G
1M
1Q
#20000000
0!
0+
06
0=
0G
0M
0Q
#25000000
1!
1+
16
1=
1G
1M
1Q
#30000000
0!
0+
06
0=
0G
0M
0Q
#35000000
1!
1+
16
1=
1G
1M
1Q
#40000000
0!
0+
06
0=
0G
0M
0Q
#45000000
1!
1+
16
1=
1G
1M
1Q
#50000000
0!
0+
06
0=
0G
0M
0Q
#55000000
1!
1+
16
1=
1G
1M
1Q
#60000000
0!
0+
06
0=
0G
0M
0Q
#65000000
1!
1+
16
1=
1G
1M
1Q
#70000000
0!
0+
06
0=
0G
0M
0Q
#75000000
1!
1+
16
1=
1G
1M
1Q
#80000000
0!
0+
06
0=
0G
0M
0Q
#85000000
1!
1+
16
1=
1G
1M
1Q
#90000000
0!
0+
06
0=
0G
0M
0Q
#95000000
1!
1+
16
1=
1G
1M
1Q
#100000000
0!
1"
0+
1,
06
18
0=
1>
0G
1H
0M
1N
0Q
1R
#105000000
1!
1+
16
1=
1G
1M
1Q
#110000000
0!
0+
06
0=
0G
0M
0Q
#115000000
1!
1+
16
1=
1G
1M
1Q
#120000000
0!
0+
06
0=
0G
0M
0Q
#125000000
1!
1+
16
1=
1G
1M
1Q
#130000000
0!
0+
06
0=
0G
0M
0Q
#135000000
1!
1+
16
1=
1G
1M
1Q
#140000000
0!
0+
06
0=
0G
0M
0Q
#145000000
1!
1+
16
1=
1G
1M
1Q
#150000000
0!
0+
06
0=
0G
0M
0Q
#155000000
1!
1+
16
1=
1G
1M
1Q
#160000000
0!
0+
06
0=
0G
0M
0Q
#165000000
1!
1+
16
1=
1G
1M
1Q
#170000000
0!
0+
06
0=
0G
0M
0Q
#175000000
1!
1+
16
1=
1G
1M
1Q
#180000000
0!
0+
06
0=
0G
0M
0Q
#185000000
1!
1+
16
1=
1G
1M
1Q
#190000000
0!
0+
06
0=
0G
0M
0Q
#195000000
1!
1$
1+
1-
16
17
1=
1G
1J
1M
1O
1Q
#200000000
0!
0+
06
0=
0G
0M
0Q
#205000000
1!
0$
1+
0-
16
07
1=
1G
0J
1M
0O
1Q
#210000000
0!
0+
06
0=
0G
0M
0Q
#215000000
1!
1+
16
1=
1G
1M
1Q
#220000000
0!
0+
06
0=
0G
0M
0Q
#225000000
1!
1+
16
1=
1G
1M
1Q
#230000000
0!
0+
06
0=
0G
0M
0Q
#235000000
1!
1+
16
1=
1G
1M
1Q
#240000000
0!
0+
06
0=
0G
0M
0Q
#245000000
1!
1+
16
1=
1G
1M
1Q
#250000000
0!
0+
06
0=
0G
0M
0Q
#255000000
1!
1+
16
1=
1G
1M
1Q
#260000000
0!
0+
06
0=
0G
0M
0Q
#265000000
1!
1+
16
1=
1G
1M
1Q
#270000000
0!
0+
06
0=
0G
0M
0Q
#275000000
1!
1+
16
1=
1G
1M
1Q
#280000000
0!
0+
06
0=
0G
0M
0Q
#285000000
1!
1+
16
1=
1G
1M
1Q
#290000000
0!
0+
06
0=
0G
0M
0Q
#295000000
1!
1$
1+
1-
16
17
1=
1G
1J
1M
1O
1Q
#300000000
0!
0+
06
0=
0G
0M
0Q
#305000000
1!
0$
1+
0-
16
07
1=
1G
0J
1M
0O
1Q
#310000000
0!
0+
06
0=
0G
0M
0Q
#315000000
1!
1+
16
1=
1G
1M
1Q
#320000000
0!
0+
06
0=
0G
0M
0Q
#325000000
1!
1+
16
1=
1G
1M
1Q
#330000000
0!
0+
06
0=
0G
0M
0Q
#335000000
1!
1+
16
1=
1G
1M
1Q
#340000000
0!
0+
06
0=
0G
0M
0Q
#345000000
1!
1+
16
1=
1G
1M
1Q
#350000000
0!
0+
06
0=
0G
0M
0Q
#355000000
1!
1+
16
1=
1G
1M
1Q
#360000000
0!
0+
06
0=
0G
0M
0Q
#365000000
1!
1+
16
1=
1G
1M
1Q
#370000000
0!
0+
06
0=
0G
0M
0Q
#375000000
1!
1+
16
1=
1G
1M
1Q
#380000000
0!
0+
06
0=
0G
0M
0Q
#385000000
1!
1+
16
1=
1G
1M
1Q
#390000000
0!
0+
06
0=
0G
0M
0Q
#395000000
1!
1$
1+
1-
16
17
1=
1G
1J
1M
1O
1Q
#400000000
0!
0+
06
0=
0G
0M
0Q
#405000000
1!
0$
1+
0-
16
07
1=
1G
0J
1M
0O
1Q
#410000000
0!
0+
06
0=
0G
0M
0Q
#415000000
1!
1+
16
1=
1G
1M
1Q
#420000000
0!
0+
06
0=
0G
0M
0Q
#425000000
1!
1+
16
1=
1G
1M
1Q
#430000000
0!
0+
06
0=
0G
0M
0Q
#435000000
1!
1+
16
1=
1G
1M
1Q
#440000000
0!
0+
06
0=
0G
0M
0Q
#445000000
1!
1+
16
1=
1G
1M
1Q
#450000000
0!
0+
06
0=
0G
0M
0Q
#455000000
1!
1+
16
1=
1G
1M
1Q
#460000000
0!
0+
06
0=
0G
0M
0Q
#465000000
1!
1+
16
1=
1G
1M
1Q
#470000000
0!
0+
06
0=
0G
0M
0Q
#475000000
1!
1+
16
1=
1G
1M
1Q
#480000000
0!
0+
06
0=
0G
0M
0Q
#485000000
1!
1+
16
1=
1G
1M
1Q
#490000000
0!
0+
06
0=
0G
0M
0Q
#495000000
1!
1$
1+
1-
16
17
1=
1G
1J
1M
1O
1Q
#500000000
0!
0+
06
0=
0G
0M
0Q
#505000000
1!
0$
1+
0-
16
07
1=
1G
0J
1M
0O
1Q
#510000000
0!
0+
06
0=
0G
0M
0Q
#515000000
1!
1+
16
1=
1G
1M
1Q
#520000000
0!
0+
06
0=
0G
0M
0Q
#525000000
1!
1+
16
1=
1G
1M
1Q
#530000000
0!
0+
06
0=
0G
0M
0Q
#535000000
1!
1+
16
1=
1G
1M
1Q
#540000000
0!
0+
06
0=
0G
0M
0Q
#545000000
1!
1+
16
1=
1G
1M
1Q
#550000000
0!
0+
06
0=
0G
0M
0Q
#555000000
1!
1+
16
1=
1G
1M
1Q
#560000000
0!
0+
06
0=
0G
0M
0Q
#565000000
1!
1+
16
1=
1G
1M
1Q
#570000000
0!
0+
06
0=
0G
0M
0Q
#575000000
1!
1+
16
1=
1G
1M
1Q
#580000000
0!
0+
06
0=
0G
0M
0Q
#585000000
1!
1+
16
1=
1G
1M
1Q
#590000000
0!
0+
06
0=
0G
0M
0Q
#595000000
1!
1$
1+
1-
16
17
1=
1G
1J
1M
1O
1Q
#600000000
0!
0+
06
0=
0G
0M
0Q
#605000000
1!
0$
1+
0-
16
07
1=
1G
0J
1M
0O
1Q
#610000000
0!
0+
06
0=
0G
0M
0Q
#615000000
1!
1+
16
1=
1G
1M
1Q
#620000000
0!
0+
06
0=
0G
0M
0Q
#625000000
1!
1+
16
1=
1G
1M
1Q
#630000000
0!
0+
06
0=
0G
0M
0Q
#635000000
1!
1+
16
1=
1G
1M
1Q
#640000000
0!
0+
06
0=
0G
0M
0Q
#645000000
1!
1+
16
1=
1G
1M
1Q
#650000000
0!
0+
06
0=
0G
0M
0Q
#655000000
1!
1+
16
1=
1G
1M
1Q
#660000000
0!
0+
06
0=
0G
0M
0Q
#665000000
1!
1+
16
1=
1G
1M
1Q
#670000000
0!
0+
06
0=
0G
0M
0Q
#675000000
1!
1+
16
1=
1G
1M
1Q
#680000000
0!
0+
06
0=
0G
0M
0Q
#685000000
1!
1+
16
1=
1G
1M
1Q
#690000000
0!
0+
06
0=
0G
0M
0Q
#695000000
1!
1$
1+
1-
16
17
1=
1G
1J
1M
1O
1Q
#700000000
0!
0+
06
0=
0G
0M
0Q
#705000000
1!
0$
1+
0-
16
07
1=
1G
0J
1M
0O
1Q
#710000000
0!
0+
06
0=
0G
0M
0Q
#715000000
1!
1+
16
1=
1G
1M
1Q
#720000000
0!
0+
06
0=
0G
0M
0Q
#725000000
1!
1+
16
1=
1G
1M
1Q
#730000000
0!
0+
06
0=
0G
0M
0Q
#735000000
1!
1+
16
1=
1G
1M
1Q
#740000000
0!
0+
06
0=
0G
0M
0Q
#745000000
1!
1+
16
1=
1G
1M
1Q
#750000000
0!
0+
06
0=
0G
0M
0Q
#755000000
1!
1+
16
1=
1G
1M
1Q
#760000000
0!
0+
06
0=
0G
0M
0Q
#765000000
1!
1+
16
1=
1G
1M
1Q
#770000000
0!
0+
06
0=
0G
0M
0Q
#775000000
1!
1+
16
1=
1G
1M
1Q
#780000000
0!
0+
06
0=
0G
0M
0Q
#785000000
1!
1+
16
1=
1G
1M
1Q
#790000000
0!
0+
06
0=
0G
0M
0Q
#795000000
1!
1$
1+
1-
16
17
1=
1G
1J
1M
1O
1Q
#800000000
0!
0+
06
0=
0G
0M
0Q
#805000000
1!
0$
1+
0-
16
07
1=
1G
0J
1M
0O
1Q
#810000000
0!
0+
06
0=
0G
0M
0Q
#815000000
1!
1+
16
1=
1G
1M
1Q
#820000000
0!
0+
06
0=
0G
0M
0Q
#825000000
1!
1+
16
1=
1G
1M
1Q
#830000000
0!
0+
06
0=
0G
0M
0Q
#835000000
1!
1+
16
1=
1G
1M
1Q
#840000000
0!
0+
06
0=
0G
0M
0Q
#845000000
1!
1+
16
1=
1G
1M
1Q
#850000000
0!
0+
06
0=
0G
0M
0Q
#855000000
1!
1+
16
1=
1G
1M
1Q
#860000000
0!
0+
06
0=
0G
0M
0Q
#865000000
1!
1+
16
1=
1G
1M
1Q
#870000000
0!
0+
06
0=
0G
0M
0Q
#875000000
1!
1+
16
1=
1G
1M
1Q
#880000000
0!
0+
06
0=
0G
0M
0Q
#885000000
1!
1+
16
1=
1G
1M
1Q
#890000000
0!
0+
06
0=
0G
0M
0Q
#895000000
1!
1$
1+
1-
16
17
1=
1G
1J
1M
1O
1Q
#900000000
0!
0+
06
0=
0G
0M
0Q
#905000000
1!
0$
1+
0-
16
07
1=
1G
0J
1M
0O
1Q
#910000000
0!
0+
06
0=
0G
0M
0Q
#915000000
1!
1+
16
1=
1G
1M
1Q
#920000000
0!
0+
06
0=
0G
0M
0Q
#925000000
1!
1+
16
1=
1G
1M
1Q
#930000000
0!
0+
06
0=
0G
0M
0Q
#935000000
1!
1+
16
1=
1G
1M
1Q
#940000000
0!
0+
06
0=
0G
0M
0Q
#945000000
1!
1+
16
1=
1G
1M
1Q
#950000000
0!
0+
06
0=
0G
0M
0Q
#955000000
1!
1+
16
1=
1G
1M
1Q
#960000000
0!
0+
06
0=
0G
0M
0Q
#965000000
1!
1+
16
1=
1G
1M
1Q
#970000000
0!
0+
06
0=
0G
0M
0Q
#975000000
1!
1+
16
1=
1G
1M
1Q
#980000000
0!
0+
06
0=
0G
0M
0Q
#985000000
1!
1+
16
1=
1G
1M
1Q
#990000000
0!
0+
06
0=
0G
0M
0Q
#995000000
1!
1$
1+
1-
16
17
1=
1G
1J
1M
1O
1Q
#1000000000
0!
0+
06
0=
0G
0M
0Q
#1005000000
1!
0$
1+
0-
16
07
1=
1G
0J
1M
0O
1Q
#1010000000
0!
0+
06
0=
0G
0M
0Q
#1015000000
1!
1+
16
1=
1G
1M
1Q
#1020000000
0!
0+
06
0=
0G
0M
0Q
#1025000000
1!
1+
16
1=
1G
1M
1Q
#1030000000
0!
0+
06
0=
0G
0M
0Q
#1035000000
1!
1+
16
1=
1G
1M
1Q
#1040000000
0!
0+
06
0=
0G
0M
0Q
#1045000000
1!
1+
16
1=
1G
1M
1Q
#1050000000
0!
0+
06
0=
0G
0M
0Q
#1055000000
1!
1+
16
1=
1G
1M
1Q
#1060000000
0!
0+
06
0=
0G
0M
0Q
#1065000000
1!
1+
16
1=
1G
1M
1Q
#1070000000
0!
0+
06
0=
0G
0M
0Q
#1075000000
1!
1+
16
1=
1G
1M
1Q
#1080000000
0!
0+
06
0=
0G
0M
0Q
#1085000000
1!
1+
16
1=
1G
1M
1Q
#1090000000
0!
0+
06
0=
0G
0M
0Q
#1095000000
1!
1$
1+
1-
16
17
1=
1G
1J
1M
1O
1Q
#1100000000
0!
0+
06
0=
0G
0M
0Q
#1105000000
1!
0$
1+
0-
16
07
1=
1G
0J
1M
0O
1Q
#1110000000
0!
0+
06
0=
0G
0M
0Q
#1115000000
1!
1+
16
1=
1G
1M
1Q
#1120000000
0!
0+
06
0=
0G
0M
0Q
#1125000000
1!
1+
16
1=
1G
1M
1Q
#1130000000
0!
0+
06
0=
0G
0M
0Q
#1135000000
1!
1+
16
1=
1G
1M
1Q
#1140000000
0!
0+
06
0=
0G
0M
0Q
#1145000000
1!
1+
16
1=
1G
1M
1Q
#1150000000
0!
0+
06
0=
0G
0M
0Q
#1155000000
1!
1+
16
1=
1G
1M
1Q
#1160000000
0!
0+
06
0=
0G
0M
0Q
#1165000000
1!
1+
16
1=
1G
1M
1Q
#1170000000
0!
0+
06
0=
0G
0M
0Q
#1175000000
1!
1+
16
1=
1G
1M
1Q
#1180000000
0!
0+
06
0=
0G
0M
0Q
#1185000000
1!
1+
16
1=
1G
1M
1Q
#1190000000
0!
0+
06
0=
0G
0M
0Q
#1195000000
1!
1$
1+
1-
16
17
1=
1G
1J
1M
1O
1Q
#1200000000
0!
0+
06
0=
0G
0M
0Q
#1205000000
1!
0$
1+
0-
16
07
1=
1G
0J
1M
0O
1Q
#1210000000
0!
0+
06
0=
0G
0M
0Q
#1215000000
1!
1+
16
1=
1G
1M
1Q
#1220000000
0!
0+
06
0=
0G
0M
0Q
#1225000000
1!
1+
16
1=
1G
1M
1Q
#1230000000
0!
0+
06
0=
0G
0M
0Q
#1235000000
1!
1+
16
1=
1G
1M
1Q
#1240000000
0!
0+
06
0=
0G
0M
0Q
#1245000000
1!
1+
16
1=
1G
1M
1Q
#1250000000
0!
0+
06
0=
0G
0M
0Q
#1255000000
1!
1+
16
1=
1G
1M
1Q
#1260000000
0!
0+
06
0=
0G
0M
0Q
#1265000000
1!
1+
16
1=
1G
1M
1Q
#1270000000
0!
0+
06
0=
0G
0M
0Q
#1275000000
1!
1+
16
1=
1G
1M
1Q
#1280000000
0!
0+
06
0=
0G
0M
0Q
#1285000000
1!
1+
16
1=
1G
1M
1Q
#1290000000
0!
0+
06
0=
0G
0M
0Q
#1295000000
1!
1$
1+
1-
16
17
1=
1G
1J
1M
1O
1Q
#1300000000
0!
0+
06
0=
0G
0M
0Q
