2a/archi/tp4/envoi_TD/envoi_octet_td.vhd
library IEEE;
use IEEE.STD_LOGIC_1164.ALL;

entity envoi_octet_td is
  Port ( clk   : in  std_logic;
         reset : in  std_logic;
         en    : in  std_logic;
         data  : in  std_logic_vector (7 downto 0);
         ack   : in  std_logic;
         txd   : out std_logic;
         busy  : out std_logic;
         terr  : out std_logic);
end envoi_octet_td;

architecture Behavioral of envoi_octet_td is

  type t_etat is (idle, envoi_data, attente_ack);
  signal etat : t_etat;

begin

  process(clk, reset)
    variable cpt_bit, cpt_ack : natural;
    variable registre : std_logic_vector(7 downto 0);

  begin

    if(reset = '0') then

      -- réinitialisation des variables du process
      -- et des signaux calculés par le process

      -- les compteurs
      cpt_bit := 7;
      cpt_ack := 5;

      -- le registre d'envoi
      registre := (others => 'U');

      -- la ligne série
      txd <= '1';

      -- l'indicateur de fonctionnement/occupation
      busy <= '0';

      -- erreur de transmission (ack pas positionné à temps)
		  terr <= '0';

      -- l'état
      etat <= idle;

    elsif(rising_edge(clk)) then

      -- erreur de transmission à '0' par défaut
      terr <= '0';

      -- front montant de l'horloge
      case etat is

        when idle =>
        -- état d'attente d'un ordre d'envoi

          if(en = '1') then
          -- un ordre est détecté
            -- on signale qu'on est occupé
            busy <= '1';

            -- on stocke l'octet à envoyer
            -- registre est une variable
            -- -> affectation immédiate
            registre := data;

            -- on initialise le compteur de bits 
            -- (variable -> affectation immédiate)
            cpt_bit := 7;

            -- on envoie le bit de poids fort (7)
            -- qui est bien dans la variable registre
            txd <= registre(cpt_bit);

            -- on change d'état
            etat <= envoi_data;
            
            -- cpt_bit variable, affectation immédiate
            cpt_bit := cpt_bit - 1;

          end if;

        when envoi_data =>

          -- état d'envoi des données
          
          -- on envoie le bit
          txd <= registre(cpt_bit);

          -- si c'était le dernier bit (0), 
          -- on a fini d'envoyer des données
          if(cpt_bit = 0) then
            -- on initialise le compteur d'attente
            -- de la confirmation
            cpt_ack := 5;
            -- on passe à l'état d'attente de la confirmation
            etat <= attente_ack;
          else
            cpt_bit := cpt_bit - 1;
          end if;

        when attente_ack =>
          -- état d'attente de la confirmation
          -- (au plus cpt_ack fronts montants de l'horloge)

          -- on décrémente le compteur d'attente
          cpt_ack := cpt_ack - 1;
          txd <= '1';

          -- si on voit la confirmation
          -- ou si on a attendu suffisamment longtemps
          -- on peut revenir à l'état initial,
          -- l'état d'attente d'un ordre
          if((ack = '1') or (cpt_ack = 0))then

            -- si c'est le ack qui n'est pas arrivé, 
            -- on indique qu'il y a eu une erreur de transmission
            if(ack = '0') then
              terr <= '1';
            end if;

            -- on signale qu'on n'est plus occupé
            busy <= '0';
            -- on revient à l'état initial
            etat <= idle;

          end if;
      end case;
    end if;
  end process;

end Behavioral;

2a/archi/tp4/envoi_TD/test_envoi_octet_td.vhd
--------------------------------------------------------------------------------
-- 
-- VHDL Test Bench Created by ISE for module: envoi_octet_td
-- 
-- Dependencies:
-- 
-- Revision:
-- Revision 0.01 - File Created
-- Additional Comments:
--
-- Notes: 
-- This testbench has been automatically generated using types std_logic and
-- std_logic_vector for the ports of the unit under test.  Xilinx recommends
-- that these types always be used for the top-level I/O of a design in order
-- to guarantee that the testbench will bind correctly to the post-implementation 
-- simulation model.
--------------------------------------------------------------------------------
LIBRARY ieee;
USE ieee.std_logic_1164.ALL;
 
-- Uncomment the following library declaration if using
-- arithmetic functions with Signed or Unsigned values
--USE ieee.numeric_std.ALL;
 
ENTITY test_envoi_octet_td IS
END test_envoi_octet_td;
 
ARCHITECTURE behavior OF test_envoi_octet_td IS 
 
    -- Component Declaration for the Unit Under Test (UUT)
 
   COMPONENT envoi_octet_td
   Port ( 
    clk   : in  std_logic;
    reset : in  std_logic;
    en    : in  std_logic;
    data  : in  std_logic_vector (7 downto 0);
    ack   : in  std_logic;
    txd   : out std_logic;
    busy  : out std_logic;
    terr  : out std_logic
   );
   END COMPONENT;
    
   --Inputs
   signal en : std_logic := '0';
   signal data : std_logic_vector(7 downto 0) := (others => '0');
   signal clk : std_logic := '0';
   signal reset : std_logic := '0';
   signal ack : std_logic := '0';

 	--Outputs
   signal txd : std_logic;
   signal busy : std_logic;
   signal terr : std_logic;

   -- Clock period definitions
   constant clk_period : time := 10 ns;

   signal txd_ref : std_logic;

BEGIN
 
  -- Instantiate the Unit Under Test (UUT)
  uut: envoi_octet_td
  PORT MAP (
            clk => clk,
            reset => reset,
            en => en,
            data => data,
            ack => ack, 
            txd => txd,
            busy => busy,
            terr => terr
           );

   -- Clock process definitions
  clk_process :process
  begin
    clk <= '0';
    wait for clk_period/2;
    clk <= '1';
    wait for clk_period/2;
  end process;

  donneur_ordre: process
  begin		
     -- hold reset state for 100 ns.
    wait for 100 ns;	
    en <= '0';
    reset <= '1';

    wait for clk_period*10;

    -- émission 1
    en <= '1';
    data <= "01001101";

    wait for clk_period;

    -- on rabaisse 'en' et on change data
    -- pour être sûr que la valeur est sauvegardée
    en <= '0';
    data <= "UUUUUUUU";

    -- on attend la fin de l'émission
    wait until busy = '0';

    wait for 5*clk_period;

    -- émission 2
    en <= '1';
    data <= "11001001";

    wait for clk_period;
    en <= '0';
    data <= "UUUUUUUU";

    wait;
  end process;

  recepteur: process
  begin

    ack <= '0';

    -- ack trop tard
    wait for 35*clk_period;
    ack <= '1';
    wait for clk_period;
    ack <= '0';

    -- ack à temps
    wait for 10*clk_period;
    ack <= '1';
    wait for clk_period;
    ack <= '0';

    wait;
  end process;

  -- valeurs attendues de txd
  txd_ref <= '1' after 0 ps,
       '0' after 205000 ps,
       '1' after 215000 ps,
       '0' after 225000 ps,
       '1' after 245000 ps,
       '0' after 265000 ps,
       '1' after 275000 ps,
       '0' after 395000 ps,
       '1' after 415000 ps,
       '0' after 425000 ps,
       '1' after 445000 ps;

  -- à chaque front descendant, on vérifie que txd et txd_ref coïncident
  process(clk)
  begin
    if(falling_edge(clk)) then
      assert(txd = txd_ref) report "*********** TXD FAUX *************"
      severity error;
    end if;
  end process;

END;

2a/archi/tp4/envoi_TD/output.vcd
$date
  Tue Oct 14 16:19:32 2025
$end
$version
  GHDL v0
$end
$timescale
  1 fs
$end
$scope module standard $end
$upscope $end
$scope module textio $end
$upscope $end
$scope module std_logic_1164 $end
$upscope $end
$scope module test_envoi_octet_td $end
$var reg 1 ! en $end
$var reg 8 " data[7:0] $end
$var reg 1 # clk $end
$var reg 1 $ reset $end
$var reg 1 % ack $end
$var reg 1 & txd $end
$var reg 1 ' busy $end
$var reg 1 ( terr $end
$var reg 1 ) txd_ref $end
$scope module uut $end
$var reg 1 * clk $end
$var reg 1 + reset $end
$var reg 1 , en $end
$var reg 8 - data[7:0] $end
$var reg 1 . ack $end
$var reg 1 / txd $end
$var reg 1 0 busy $end
$var reg 1 1 terr $end
$comment etat is not handled $end
$upscope $end
$upscope $end
$enddefinitions $end
#0
0!
b00000000 "
0#
0$
0%
1&
0'
0(
1)
0*
0+
0,
b00000000 -
0.
1/
00
01
#5000000
1#
1*
#10000000
0#
0*
#15000000
1#
1*
#20000000
0#
0*
#25000000
1#
1*
#30000000
0#
0*
#35000000
1#
1*
#40000000
0#
0*
#45000000
1#
1*
#50000000
0#
0*
#55000000
1#
1*
#60000000
0#
0*
#65000000
1#
1*
#70000000
0#
0*
#75000000
1#
1*
#80000000
0#
0*
#85000000
1#
1*
#90000000
0#
0*
#95000000
1#
1*
#100000000
0#
1$
0*
1+
#105000000
1#
1*
#110000000
0#
0*
#115000000
1#
1*
#120000000
0#
0*
#125000000
1#
1*
#130000000
0#
0*
#135000000
1#
1*
#140000000
0#
0*
#145000000
1#
1*
#150000000
0#
0*
#155000000
1#
1*
#160000000
0#
0*
#165000000
1#
1*
#170000000
0#
0*
#175000000
1#
1*
#180000000
0#
0*
#185000000
1#
1*
#190000000
0#
0*
#195000000
1#
1*
#200000000
1!
b01001101 "
0#
0*
1,
b01001101 -
#205000000
1#
0&
1'
0)
1*
0/
10
#210000000
0!
bUUUUUUUU "
0#
0*
0,
bUUUUUUUU -
#215000000
1#
1&
1)
1*
1/
#220000000
0#
0*
#225000000
1#
0&
0)
1*
0/
#230000000
0#
0*
#235000000
1#
1*
#240000000
0#
0*
#245000000
1#
1&
1)
1*
1/
#250000000
0#
0*
#255000000
1#
1*
#260000000
0#
0*
#265000000
1#
0&
0)
1*
0/
#270000000
0#
0*
#275000000
1#
1&
1)
1*
1/
#280000000
0#
0*
#285000000
1#
1*
#290000000
0#
0*
#295000000
1#
1*
#300000000
0#
0*
#305000000
1#
1*
#310000000
0#
0*
#315000000
1#
1*
#320000000
0#
0*
#325000000
1#
0'
1(
1*
00
11
#330000000
0#
0*
#335000000
1#
0(
1*
01
#340000000
0#
0*
#345000000
1#
1*
#350000000
0#
1%
0*
1.
#355000000
1#
1*
#360000000
0#
0%
0*
0.
#365000000
1#
1*
#370000000
0#
0*
#375000000
1!
b11001001 "
1#
1'
1*
1,
b11001001 -
10
#380000000
0#
0*
#385000000
0!
bUUUUUUUU "
1#
1*
0,
bUUUUUUUU -
#390000000
0#
0*
#395000000
1#
0&
0)
1*
0/
#400000000
0#
0*
#405000000
1#
1*
#410000000
0#
0*
#415000000
1#
1&
1)
1*
1/
#420000000
0#
0*
#425000000
1#
0&
0)
1*
0/
#430000000
0#
0*
#435000000
1#
1*
#440000000
0#
0*
#445000000
1#
1&
1)
1*
1/
#450000000
0#
0*
#455000000
1#
1*
#460000000
0#
1%
0*
1.
#465000000
1#
0'
1*
00
#470000000
0#
0%
0*
0.
