2a/archi/projet/ER_1OCTET/er_1octet.vhd
library IEEE;
use IEEE.STD_LOGIC_1164.ALL;

entity er_1octet is
  port ( rst : in std_logic ;
         clk : in std_logic ;
         en : in std_logic ;
         din : in std_logic_vector (7 downto 0) ;
         miso : in std_logic ;
         sclk : out std_logic ;
         mosi : out std_logic ;
         dout : out std_logic_vector (7 downto 0) ;
         busy : out std_logic);
end er_1octet;

architecture behavioral_3 of er_1octet is
  type t_etat is (REPOS, RECEPTION, ENVOI);
  signal registre : std_logic_vector (7 downto 0);
  signal etat : t_etat;
begin
  process(rst, clk)
    variable cpt : natural;
  begin
    -- reset
    if (rst = '0') then
      etat <= REPOS;
      sclk <= '1';
      busy <= '0';

    -- horloge montante
    elsif (rising_edge(clk)) then
      case etat is
        when REPOS =>
          if (en = '1') then
            cpt := 7;
            busy <= '1';
            registre <= din;
            sclk <= '0';
            mosi <= din(cpt);
            etat <= RECEPTION;
          end if;

        when RECEPTION =>
          sclk <= '1';
          if (cpt > 0) then
            registre(cpt) <= miso;
            cpt := cpt - 1;
            etat <= ENVOI;
          else
            busy <= '0';
            dout(7 downto 1) <= registre(7 downto 1);
            dout(0) <= miso;
            etat <= REPOS;
          end if;

        when ENVOI =>
          sclk <= '0';
          mosi <= registre(cpt);
          etat <= RECEPTION;
      end case;
    end if;
  end process;
end behavioral_3;

2a/archi/mini-projet/ER_1OCTET/test_er_1octet_simple.vhd
library IEEE;
use IEEE.STD_LOGIC_1164.ALL;

entity test_er_1octet1 is
  end test_er_1octet1;

architecture behavior of test_er_1octet1 is

  component er_1octet
    port ( rst : in std_logic;
           clk : in std_logic;
           en : in std_logic;
           din : in std_logic_vector (7 downto 0);
           miso : in std_logic;
           sclk : out std_logic;
           mosi : out std_logic;
           dout : out std_logic_vector (7 downto 0);
           busy : out std_logic);
  end component;

  --Inputs
  signal clk : std_logic := '0';
  signal reset : std_logic := '0';
  signal en : std_logic := '0';
  signal din : std_logic_vector(7 downto 0) := (others => '0');
  signal miso : std_logic := '0';

  --Outputs
  signal busy : std_logic;
  signal dout : std_logic_vector(7 downto 0);
  signal sclk : std_logic;
  signal mosi : std_logic;

  --References
  signal busy_ref : std_logic;
  signal dout_ref : std_logic_vector(7 downto 0);
  signal sclk_ref : std_logic;
  signal mosi_ref : std_logic;

  -- Clock period definitions
  constant clk_period : time := 10 ns;

begin

  m : er_1octet
  port map ( clk => clk,
             rst => reset,
             en => en,
             busy => busy,
             din => din,
             dout => dout,
             sclk => sclk,
             miso => miso,
             mosi => mosi
           );

  clk_process : process
  begin
    clk <= '0';
    wait for clk_period/2;
    clk <= '1';
    wait for clk_period/2;
  end process;


  -- Stimulus process
  stim_proc: process
  begin                
    -- hold reset state for 100 ns.
    wait for 100 ns;  
    reset <= '1';

    wait for clk_period*10;

    -- insert stimulus here

    din <= "10110101";

    en <= '1';

    wait for clk_period;

    en <= '0';
    din <= (others => 'U');

    wait for 21*clk_period;

    din <= "00110100";

    en <= '1';

    wait for clk_period;

    en <= '0';
    din <= (others => 'U');

    wait;
  end process;

  genere_miso : process(clk, reset)

    variable cpt : natural;

  begin

    if(reset = '0') then
      miso <= '0';
      cpt := 0;
    elsif(falling_edge(clk)) then
      cpt := (cpt + 1) mod 7;
      if(cpt < 3) then
        miso <= '0';
      else
        miso <= '1';
      end if;                  
    end if;

  end process genere_miso;

  --
  -- pour vérifier si mosi, sclk et busy et dout sont corrects

  busy_ref <= '0' after 0 fs,
              '1' after 205000000 fs,
              '0' after 355000000 fs,
              '1' after 425000000 fs,
              '0' after 575000000 fs;

  dout_ref <= "UUUUUUUU" after 0 fs,
              "10011011" after 355000000 fs,
              "10110011" after 575000000 fs;

  mosi_ref <= 'U' after 0 ps,
              '1' after 205000 ps,
              '0' after 225000 ps,
              '1' after 245000 ps,
              '0' after 285000 ps,
              '1' after 305000 ps,
              '0' after 325000 ps,
              '1' after 345000 ps,
              '0' after 425000 ps,
              '1' after 465000 ps,
              '0' after 505000 ps,
              '1' after 525000 ps,
              '0' after 545000 ps;

  sclk_ref <= '1' after 0 ps,
              '0' after 205000 ps,
              '1' after 215000 ps,
              '0' after 225000 ps,
              '1' after 235000 ps,
              '0' after 245000 ps,
              '1' after 255000 ps,
              '0' after 265000 ps,
              '1' after 275000 ps,
              '0' after 285000 ps,
              '1' after 295000 ps,
              '0' after 305000 ps,
              '1' after 315000 ps,
              '0' after 325000 ps,
              '1' after 335000 ps,
              '0' after 345000 ps,
              '1' after 355000 ps,
              '0' after 425000 ps,
              '1' after 435000 ps,
              '0' after 445000 ps,
              '1' after 455000 ps,
              '0' after 465000 ps,
              '1' after 475000 ps,
              '0' after 485000 ps,
              '1' after 495000 ps,
              '0' after 505000 ps,
              '1' after 515000 ps,
              '0' after 525000 ps,
              '1' after 535000 ps,
              '0' after 545000 ps,
              '1' after 555000 ps,
              '0' after 565000 ps,
              '1' after 575000 ps;

  process(clk)
  begin
    if(falling_edge(clk)) then
      assert(mosi = mosi_ref) report "mosi faux"
      severity error;
      assert(sclk = sclk_ref) report "sclk faux"
      severity error;
      assert(busy = busy_ref) report "busy faux"
      severity error;
      assert(dout = dout_ref) report "dout faux"
      severity error;
    end if;
  end process;

end behavior;

2a/archi/projet/ER_1OCTET/output1.vcd
$date
  Tue Nov  4 15:27:27 2025
$end
$version
  GHDL v0
$end
$timescale
  1 fs
$end
$scope module standard $end
$upscope $end
$scope module textio $end
$upscope $end
$scope module std_logic_1164 $end
$upscope $end
$scope module test_er_1octet1 $end
$var reg 1 ! clk $end
$var reg 1 " reset $end
$var reg 1 # en $end
$var reg 8 $ din[7:0] $end
$var reg 1 % miso $end
$var reg 1 & busy $end
$var reg 8 ' dout[7:0] $end
$var reg 1 ( sclk $end
$var reg 1 ) mosi $end
$var reg 1 * busy_ref $end
$var reg 8 + dout_ref[7:0] $end
$var reg 1 , sclk_ref $end
$var reg 1 - mosi_ref $end
$scope module m $end
$var reg 1 . rst $end
$var reg 1 / clk $end
$var reg 1 0 en $end
$var reg 8 1 din[7:0] $end
$var reg 1 2 miso $end
$var reg 1 3 sclk $end
$var reg 1 4 mosi $end
$var reg 8 5 dout[7:0] $end
$var reg 1 6 busy $end
$var reg 8 7 registre[7:0] $end
$comment etat is not handled $end
$upscope $end
$upscope $end
$enddefinitions $end
#0
0!
0"
0#
b00000000 $
0%
0&
bUUUUUUUU '
1(
U)
0*
bUUUUUUUU +
1,
U-
0.
0/
00
b00000000 1
02
13
U4
bUUUUUUUU 5
06
bUUUUUUUU 7
#5000000
1!
1/
#10000000
0!
0/
#15000000
1!
1/
#20000000
0!
0/
#25000000
1!
1/
#30000000
0!
0/
#35000000
1!
1/
#40000000
0!
0/
#45000000
1!
1/
#50000000
0!
0/
#55000000
1!
1/
#60000000
0!
0/
#65000000
1!
1/
#70000000
0!
0/
#75000000
1!
1/
#80000000
0!
0/
#85000000
1!
1/
#90000000
0!
0/
#95000000
1!
1/
#100000000
0!
1"
1.
0/
#105000000
1!
1/
#110000000
0!
0/
#115000000
1!
1/
#120000000
0!
1%
0/
12
#125000000
1!
1/
#130000000
0!
0/
#135000000
1!
1/
#140000000
0!
0/
#145000000
1!
1/
#150000000
0!
0/
#155000000
1!
1/
#160000000
0!
0%
0/
02
#165000000
1!
1/
#170000000
0!
0/
#175000000
1!
1/
#180000000
0!
0/
#185000000
1!
1/
#190000000
0!
1%
0/
12
#195000000
1!
1/
#200000000
0!
1#
b10110101 $
0/
10
b10110101 1
#205000000
1!
1&
0(
1)
1*
0,
1-
1/
03
14
16
b10110101 7
#210000000
0!
0#
bUUUUUUUU $
0/
00
bUUUUUUUU 1
#215000000
1!
1(
1,
1/
13
#220000000
0!
0/
#225000000
1!
0(
0)
0,
0-
1/
03
04
#230000000
0!
0%
0/
02
#235000000
1!
1(
1,
1/
13
#240000000
0!
0/
#245000000
1!
0(
1)
0,
1-
1/
03
14
#250000000
0!
0/
#255000000
1!
1(
1,
1/
13
b10010101 7
#260000000
0!
1%
0/
12
#265000000
1!
0(
0,
1/
03
#270000000
0!
0/
#275000000
1!
1(
1,
1/
13
#280000000
0!
0/
#285000000
1!
0(
0)
0,
0-
1/
03
04
#290000000
0!
0/
#295000000
1!
1(
1,
1/
13
b10011101 7
#300000000
0!
0%
0/
02
#305000000
1!
0(
1)
0,
1-
1/
03
14
#310000000
0!
0/
#315000000
1!
1(
1,
1/
13
b10011001 7
#320000000
0!
0/
#325000000
1!
0(
0)
0,
0-
1/
03
04
#330000000
0!
1%
0/
12
#335000000
1!
1(
1,
1/
13
b10011011 7
#340000000
0!
0/
#345000000
1!
0(
1)
0,
1-
1/
03
14
#350000000
0!
0/
#355000000
1!
0&
b10011011 '
1(
0*
b10011011 +
1,
1/
13
b10011011 5
06
#360000000
0!
0/
#365000000
1!
1/
#370000000
0!
0%
0/
02
#375000000
1!
1/
#380000000
0!
0/
#385000000
1!
1/
#390000000
0!
0/
#395000000
1!
1/
#400000000
0!
1%
0/
12
#405000000
1!
1/
#410000000
0!
0/
#415000000
1!
1/
#420000000
0!
1#
b00110100 $
0/
10
b00110100 1
#425000000
1!
1&
0(
0)
1*
0,
0-
1/
03
04
16
b00110100 7
#430000000
0!
0#
bUUUUUUUU $
0/
00
bUUUUUUUU 1
#435000000
1!
1(
1,
1/
13
b10110100 7
#440000000
0!
0%
0/
02
#445000000
1!
0(
0,
1/
03
#450000000
0!
0/
#455000000
1!
1(
1,
1/
13
#460000000
0!
0/
#465000000
1!
0(
1)
0,
1-
1/
03
14
#470000000
0!
1%
0/
12
#475000000
1!
1(
1,
1/
13
#480000000
0!
0/
#485000000
1!
0(
0,
1/
03
#490000000
0!
0/
#495000000
1!
1(
1,
1/
13
#500000000
0!
0/
#505000000
1!
0(
0)
0,
0-
1/
03
04
#510000000
0!
0%
0/
02
#515000000
1!
1(
1,
1/
13
#520000000
0!
0/
#525000000
1!
0(
1)
0,
1-
1/
03
14
#530000000
0!
0/
#535000000
1!
1(
1,
1/
13
b10110000 7
#540000000
0!
1%
0/
12
#545000000
1!
0(
0)
0,
0-
1/
03
04
#550000000
0!
0/
#555000000
1!
1(
1,
1/
13
b10110010 7
#560000000
0!
0/
#565000000
1!
0(
0,
1/
03
#570000000
0!
0/
#575000000
1!
0&
b10110011 '
1(
0*
b10110011 +
1,
1/
13
b10110011 5
06
#580000000
0!
0%
0/
02
#585000000
1!
1/
#590000000
0!
0/
#595000000
1!
1/
#600000000
0!
0/
#605000000
1!
1/
#610000000
0!
1%
0/
12
#615000000
1!
1/
#620000000
0!
0/
#625000000
1!
1/
#630000000
0!
0/
#635000000
1!
1/
#640000000
0!
0/
#645000000
1!
1/
#650000000
0!
0%
0/
02
#655000000
1!
1/
#660000000
0!
0/
#665000000
1!
1/
#670000000
0!
0/
#675000000
1!
1/
#680000000
0!
1%
0/
12
#685000000
1!
1/
#690000000
0!
0/
#695000000
1!
1/
#700000000
0!
0/
#705000000
1!
1/
#710000000
0!
0/
#715000000
1!
1/
#720000000
0!
0%
0/
02
#725000000
1!
1/
#730000000
0!
0/
#735000000
1!
1/
#740000000
0!
0/
#745000000
1!
1/
#750000000
0!
1%
0/
12
#755000000
1!
1/
#760000000
0!
0/
#765000000
1!
1/
#770000000
0!
0/
#775000000
1!
1/
#780000000
0!
0/
#785000000
1!
1/
#790000000
0!
0%
0/
02
#795000000
1!
1/
#800000000
0!
0/
#805000000
1!
1/
#810000000
0!
0/
#815000000
1!
1/
#820000000
0!
1%
0/
12
#825000000
1!
1/
#830000000
0!
0/
#835000000
1!
1/
#840000000
0!
0/
#845000000
1!
1/
#850000000
0!
0/
#855000000
1!
1/
#860000000
0!
0%
0/
02
#865000000
1!
1/
#870000000
0!
0/
#875000000
1!
1/
#880000000
0!
0/
#885000000
1!
1/
#890000000
0!
1%
0/
12
#895000000
1!
1/
#900000000
0!
0/
#905000000
1!
1/
#910000000
0!
0/
#915000000
1!
1/
#920000000
0!
0/
#925000000
1!
1/
#930000000
0!
0%
0/
02
#935000000
1!
1/
#940000000
0!
0/
#945000000
1!
1/
#950000000
0!
0/
#955000000
1!
1/
#960000000
0!
1%
0/
12
#965000000
1!
1/
#970000000
0!
0/
#975000000
1!
1/
#980000000
0!
0/
#985000000
1!
1/
#990000000
0!
0/
#995000000
1!
1/
#1000000000
0!
0%
0/
02
